muchscript/__init__.py
muchscript/builtin.py
muchscript/datatypes.py
muchscript/dotdoe.py
muchscript/error_printing.py
muchscript/errors.py
muchscript/functions.py
muchscript/interprete.py
muchscript/lexer.py
muchscript/muchscript.py
muchscript/nodes.py
muchscript/parsers.py
muchscript/position.py
muchscript/run.py
muchscript/runtime.py
muchscript/tokens.py
muchscript/value.py
muchscript-0.1.4.data/scripts/much
muchscript-0.1.4.dist-info/LICENSE
muchscript-0.1.4.dist-info/METADATA
muchscript-0.1.4.dist-info/WHEEL
muchscript-0.1.4.dist-info/top_level.txt
muchscript-0.1.4.dist-info/RECORD
