Metadata-Version: 2.1
Name: muchscript
Version: 0.1.4
Summary: A crypto language inspired by Doge and the Dogefather.
Home-page: https://github.com/shaurya-blip/muchscript/
Author: Shaurya Pratap Singh
Author-email: shaurya.p.singh21@gmail.com
License: MIT
Platform: UNKNOWN
License-File: LICENSE
